dawnlog/Logger.py
dawnlog/__init__.py
dawnlog-0.0.1.dist-info/METADATA
dawnlog-0.0.1.dist-info/WHEEL
dawnlog-0.0.1.dist-info/top_level.txt
dawnlog-0.0.1.dist-info/RECORD
